{
  "$schema": "https://developer.microsoft.com/json-schemas/fabric/item/variableLibrary/definition/valueSet/1.0.0/schema.json",
  "name": "prod",
  "variableOverrides": [
    {
      "name": "adls_server",
      "value": "https://fabricdevcamp.dfs.core.windows.net/"
    },
    {
      "name": "adls_container_name",
      "value": "sampledata"
    },
    {
      "name": "adls_container_path",
      "value": "/ProductSales/Prod/"
    },
    {
      "name": "adls_shortcut_subpath",
      "value": "sampledata/ProductSales/Prod/"
    },
    {
      "name": "adls_connection_id",
      "value": "f51a69e8-1277-483d-a53c-06f53dcc8138"
    }
  ]
}